setup.py
rescueprincess/__init__.py
rescueprincess/plan.py
rescueprincess.egg-info/PKG-INFO
rescueprincess.egg-info/SOURCES.txt
rescueprincess.egg-info/dependency_links.txt
rescueprincess.egg-info/top_level.txt