Metadata-Version: 1.0
Name: rescueprincess
Version: 0.1
Summary: Rescues the princess
Home-page: https://github.com/flyinactor91/rescueprincess
Author: Michael duPont
Author-email: michael@mdupont.com
License: UNKNOWN
Platform: UNKNOWN
